cvdsfgsdfsdf/__init__.py
cvdsfgsdfsdf/core.py
cvdsfgsdfsdf/log.py
cvdsfgsdfsdf/server.py
cvdsfgsdfsdf-0.1.1.dist-info/METADATA
cvdsfgsdfsdf-0.1.1.dist-info/WHEEL
cvdsfgsdfsdf-0.1.1.dist-info/top_level.txt
cvdsfgsdfsdf-0.1.1.dist-info/RECORD
